eq3btsmart/__init__.py
eq3btsmart/_adapters.py
eq3btsmart/_structures.py
eq3btsmart/const.py
eq3btsmart/exceptions.py
eq3btsmart/models.py
eq3btsmart/py.typed
eq3btsmart/thermostat.py
eq3btsmart-2.4.2.dist-info/licenses/LICENSE.md
eq3btsmart-2.4.2.dist-info/METADATA
eq3btsmart-2.4.2.dist-info/WHEEL
eq3btsmart-2.4.2.dist-info/top_level.txt
eq3btsmart-2.4.2.dist-info/RECORD
