Metadata-Version: 2.4
Name: eq3btsmart
Version: 2.4.2
Summary: Python library to interact with eQ-3 Bluetooth Smart thermostats
Author-email: Lennard Beers <l.beers@outlook.de>
Maintainer-email: Lennard Beers <l.beers@outlook.de>
License: Copyright 2024 Lennard Beers
Project-URL: Repository, https://github.com/eulemitkeule/eq3btsmart
Project-URL: Documentation, https://github.com/eulemitkeule/eq3btsmart/blob/master/README.md
Project-URL: Changelog, https://github.com/EuleMitKeule/eq3btsmart/releases
Project-URL: Issues, https://github.com/eulemitkeule/eq3btsmart/issues
Project-URL: Download, https://pypi.org/project/eq3btsmart/
Keywords: eq3,eq3btsmart,thermostat,bluetooth,smart,homeassistant,bleak,asyncio,library
Classifier: Development Status :: 5 - Production/Stable
Classifier: Intended Audience :: Developers
Classifier: License :: OSI Approved :: MIT License
Classifier: Programming Language :: Python :: 3
Classifier: Programming Language :: Python :: 3.13
Requires-Python: >=3.12
License-File: LICENSE.md
Requires-Dist: bleak
Requires-Dist: bleak-retry-connector
Requires-Dist: construct-typing
Dynamic: license-file
